console.py
logg.py
properties.py
mime_common-0.2.8.dist-info/LICENSE.txt
mime_common-0.2.8.dist-info/METADATA
mime_common-0.2.8.dist-info/WHEEL
mime_common-0.2.8.dist-info/top_level.txt
mime_common-0.2.8.dist-info/RECORD
