Metadata-Version: 2.1
Name: mime-common
Version: 0.2.8
Summary: Some reusable libraries for properties, logging, console
Home-page: https://www.vegvesen.no
Author: Bjørne Malmanger
Author-email: bjorne.malmanger@vegvesen.no
License: UNKNOWN
Platform: UNKNOWN
Classifier: Programming Language :: Python :: 3
Classifier: Programming Language :: Python :: 3.8
Classifier: Programming Language :: Python :: 3.9
Classifier: Programming Language :: Python :: 3.10
Classifier: Programming Language :: Python :: 3.11
Classifier: Programming Language :: Python :: 3.12
Classifier: License :: OSI Approved :: MIT License
Classifier: Operating System :: OS Independent
Requires-Python: >=3.8
Provides-Extra: dev
Requires-Dist: pytest (>=7.4) ; extra == 'dev'
Requires-Dist: twine (>=4.0.2) ; extra == 'dev'
